{
  "id": "tx_m_3209609_ne_14_060_20220704",
  "bbox": [
    -96.941699,
    32.809201,
    -96.870252,
    32.878791
  ],
  "type": "Feature",
  "links": [
    {
      "rel": "collection",
      "type": "application/json",
      "href": "https://planetarycomputer.microsoft.com/api/stac/v1/collections/naip"
    },
    {
      "rel": "root",
      "href": "./catalog.json",
      "type": "application/json",
      "title": "NAIP: National Agriculture Imagery Program"
    },
    {
      "rel": "parent",
      "href": "./catalog.json",
      "type": "application/json",
      "title": "NAIP: National Agriculture Imagery Program"
    }
  ],
  "assets": {
    "image": {
      "href": "https://naipeuwest.blob.core.windows.net/naip/v002/tx/2022/tx_060cm_2022/32096/m_3209609_ne_14_060_20220704.tif",
      "type": "image/tiff; application=geotiff; profile=cloud-optimized",
      "roles": [
        "data"
      ],
      "title": "RGBIR COG tile",
      "eo:bands": [
        {
          "name": "Red",
          "common_name": "red"
        },
        {
          "name": "Green",
          "common_name": "green"
        },
        {
          "name": "Blue",
          "common_name": "blue"
        },
        {
          "name": "NIR",
          "common_name": "nir",
          "description": "near-infrared"
        }
      ]
    },
    "thumbnail": {
      "href": "https://naipeuwest.blob.core.windows.net/naip/v002/tx/2022/tx_060cm_2022/32096/m_3209609_ne_14_060_20220704.200.jpg",
      "type": "image/jpeg",
      "roles": [
        "thumbnail"
      ],
      "title": "Thumbnail"
    },
    "tilejson": {
      "title": "TileJSON with default rendering",
      "href": "https://planetarycomputer.microsoft.com/api/data/v1/item/tilejson.json?collection=naip&item=tx_m_3209609_ne_14_060_20220704&assets=image&asset_bidx=image%7C1%2C2%2C3&format=png",
      "type": "application/json",
      "roles": [
        "tiles"
      ]
    },
    "rendered_preview": {
      "title": "Rendered preview",
      "rel": "preview",
      "href": "https://planetarycomputer.microsoft.com/api/data/v1/item/preview.png?collection=naip&item=tx_m_3209609_ne_14_060_20220704&assets=image&asset_bidx=image%7C1%2C2%2C3&format=png",
      "roles": [
        "overview"
      ],
      "type": "image/png"
    }
  },
  "geometry": {
    "type": "Polygon",
    "coordinates": [
      [
        [
          -96.871886,
          32.809201
        ],
        [
          -96.870252,
          32.87762
        ],
        [
          -96.940119,
          32.878791
        ],
        [
          -96.941699,
          32.810369
        ],
        [
          -96.871886,
          32.809201
        ]
      ]
    ]
  },
  "collection": "naip",
  "properties": {
    "gsd": 0.6,
    "datetime": "2022-07-04T16:00:00Z",
    "naip:year": "2022",
    "proj:bbox": [
      692705.4,
      3632140.8,
      699245.4,
      3639730.8
    ],
    "proj:epsg": 26914,
    "providers": [
      {
        "url": "https://www.fsa.usda.gov/programs-and-services/aerial-photography/imagery-programs/naip-imagery/",
        "name": "USDA Farm Service Agency",
        "roles": [
          "producer",
          "licensor"
        ]
      }
    ],
    "naip:state": "tx",
    "proj:shape": [
      12650,
      10900
    ],
    "proj:centroid": {
      "lat": 32.844,
      "lon": -96.90599
    },
    "proj:transform": [
      0.6,
      0.0,
      692705.4,
      0.0,
      -0.6,
      3639730.8,
      0.0,
      0.0,
      1.0
    ]
  },
  "stac_extensions": [
    "https://stac-extensions.github.io/eo/v1.0.0/schema.json",
    "https://stac-extensions.github.io/projection/v1.0.0/schema.json"
  ],
  "stac_version": "1.0.0"
}